[
    {
        "CurrencyIsoCode": "INR",
        "GlobalKey": "ARTLUpdateRequest6401938878586495",
        "InputFieldName": "Req",
        "IsDisabled": false,
        "IsRequiredForUpsert": false,
        "IsUpsertKey": false,
        "Name": "ARTLUpdateRequest",
        "OmniDataTransformationId": {
            "Name": "ARTLUpdateRequest",
            "VlocityDataPackType": "VlocityMatchingKeyObject",
            "VlocityMatchingRecordSourceKey": "OmniDataTransform/ARTLUpdateRequest",
            "VlocityRecordSObjectType": "OmniDataTransform"
        },
        "OutputCreationSequence": 1,
        "OutputFieldName": "ARTL_RequestPayload__c",
        "OutputObjectName": "Execution_Log__c",
        "VlocityDataPackType": "SObject",
        "VlocityRecordSObjectType": "OmniDataTransformItem"
    },
    {
        "CurrencyIsoCode": "INR",
        "GlobalKey": "ARTLUpdateRequest46268442640648155",
        "InputFieldName": "Resp",
        "IsDisabled": false,
        "IsRequiredForUpsert": false,
        "IsUpsertKey": false,
        "Name": "ARTLUpdateRequest",
        "OmniDataTransformationId": {
            "Name": "ARTLUpdateRequest",
            "VlocityDataPackType": "VlocityMatchingKeyObject",
            "VlocityMatchingRecordSourceKey": "OmniDataTransform/ARTLUpdateRequest",
            "VlocityRecordSObjectType": "OmniDataTransform"
        },
        "OutputCreationSequence": 1,
        "OutputFieldName": "ARTL_ResponsePayload__c",
        "OutputObjectName": "Execution_Log__c",
        "VlocityDataPackType": "SObject",
        "VlocityRecordSObjectType": "OmniDataTransformItem"
    },
    {
        "CurrencyIsoCode": "INR",
        "FilterOperator": "=",
        "GlobalKey": "ARTLUpdateRequest5884467676330287",
        "IsDisabled": true,
        "IsRequiredForUpsert": false,
        "IsUpsertKey": false,
        "MigrationValue": "FAKEMAPPING",
        "Name": "ARTLUpdateRequest",
        "OmniDataTransformationId": {
            "Name": "ARTLUpdateRequest",
            "VlocityDataPackType": "VlocityMatchingKeyObject",
            "VlocityMatchingRecordSourceKey": "OmniDataTransform/ARTLUpdateRequest",
            "VlocityRecordSObjectType": "OmniDataTransform"
        },
        "OutputCreationSequence": 1,
        "OutputFieldName": "Id",
        "OutputObjectName": "Execution_Log__c",
        "VlocityDataPackType": "SObject",
        "VlocityRecordSObjectType": "OmniDataTransformItem"
    },
    {
        "CurrencyIsoCode": "INR",
        "GlobalKey": "ARTLUpdateRequest26623536810813064",
        "InputFieldName": "taskId",
        "IsDisabled": false,
        "IsRequiredForUpsert": false,
        "IsUpsertKey": true,
        "Name": "ARTLUpdateRequest",
        "OmniDataTransformationId": {
            "Name": "ARTLUpdateRequest",
            "VlocityDataPackType": "VlocityMatchingKeyObject",
            "VlocityMatchingRecordSourceKey": "OmniDataTransform/ARTLUpdateRequest",
            "VlocityRecordSObjectType": "OmniDataTransform"
        },
        "OutputCreationSequence": 1,
        "OutputFieldName": "Name",
        "OutputObjectName": "Execution_Log__c",
        "VlocityDataPackType": "SObject",
        "VlocityRecordSObjectType": "OmniDataTransformItem"
    },
    {
        "CurrencyIsoCode": "INR",
        "GlobalKey": "ARTLUpdateRequestCustom6094",
        "InputFieldName": "AltKey",
        "IsDisabled": false,
        "IsRequiredForUpsert": false,
        "IsUpsertKey": false,
        "Name": "ARTLUpdateRequest",
        "OmniDataTransformationId": {
            "Name": "ARTLUpdateRequest",
            "VlocityDataPackType": "VlocityMatchingKeyObject",
            "VlocityMatchingRecordSourceKey": "OmniDataTransform/ARTLUpdateRequest",
            "VlocityRecordSObjectType": "OmniDataTransform"
        },
        "OutputCreationSequence": 2,
        "OutputFieldName": "ARTL_Alt_Key_API__c",
        "OutputObjectName": "ARTL_Task_Integration_Logs__c",
        "VlocityDataPackType": "SObject",
        "VlocityRecordSObjectType": "OmniDataTransformItem"
    },
    {
        "CurrencyIsoCode": "INR",
        "GlobalKey": "ARTLUpdateRequestCustom1640",
        "InputFieldName": "OrderId",
        "IsDisabled": false,
        "IsRequiredForUpsert": false,
        "IsUpsertKey": false,
        "Name": "ARTLUpdateRequest",
        "OmniDataTransformationId": {
            "Name": "ARTLUpdateRequest",
            "VlocityDataPackType": "VlocityMatchingKeyObject",
            "VlocityMatchingRecordSourceKey": "OmniDataTransform/ARTLUpdateRequest",
            "VlocityRecordSObjectType": "OmniDataTransform"
        },
        "OutputCreationSequence": 2,
        "OutputFieldName": "ARTL_OrderId__c",
        "OutputObjectName": "ARTL_Task_Integration_Logs__c",
        "VlocityDataPackType": "SObject",
        "VlocityRecordSObjectType": "OmniDataTransformItem"
    },
    {
        "CurrencyIsoCode": "INR",
        "GlobalKey": "ARTLUpdateRequestCustom3454",
        "InputFieldName": "Req",
        "IsDisabled": false,
        "IsRequiredForUpsert": false,
        "IsUpsertKey": false,
        "Name": "ARTLUpdateRequest",
        "OmniDataTransformationId": {
            "Name": "ARTLUpdateRequest",
            "VlocityDataPackType": "VlocityMatchingKeyObject",
            "VlocityMatchingRecordSourceKey": "OmniDataTransform/ARTLUpdateRequest",
            "VlocityRecordSObjectType": "OmniDataTransform"
        },
        "OutputCreationSequence": 2,
        "OutputFieldName": "ARTL_Response__c",
        "OutputObjectName": "ARTL_Task_Integration_Logs__c",
        "VlocityDataPackType": "SObject",
        "VlocityRecordSObjectType": "OmniDataTransformItem"
    },
    {
        "CurrencyIsoCode": "INR",
        "FilterOperator": "=",
        "GlobalKey": "ARTLUpdateRequestCustom2384",
        "IsDisabled": true,
        "IsRequiredForUpsert": false,
        "IsUpsertKey": false,
        "MigrationValue": "FAKEMAPPING",
        "Name": "ARTLUpdateRequest",
        "OmniDataTransformationId": {
            "Name": "ARTLUpdateRequest",
            "VlocityDataPackType": "VlocityMatchingKeyObject",
            "VlocityMatchingRecordSourceKey": "OmniDataTransform/ARTLUpdateRequest",
            "VlocityRecordSObjectType": "OmniDataTransform"
        },
        "OutputCreationSequence": 2,
        "OutputFieldName": "Id",
        "OutputObjectName": "ARTL_Task_Integration_Logs__c",
        "VlocityDataPackType": "SObject",
        "VlocityRecordSObjectType": "OmniDataTransformItem"
    }
]