{
    "CurrencyIsoCode": "INR",
    "IsActive": true,
    "IsOmniScriptEmbeddable": false,
    "Name": "SV_FailedResponseList",
    "OmniProcessId": {
        "Name": "NBAResponseToSolace",
        "VlocityDataPackType": "VlocityMatchingKeyObject",
        "VlocityMatchingRecordSourceKey": "OmniProcess/ARTL/NBAResponseToSolace/Procedure",
        "VlocityRecordSObjectType": "OmniProcess"
    },
    "ParentElementId": {
        "Name": "ConditionalBlock2",
        "OmniProcessId": {
            "Name": "NBAResponseToSolace",
            "VlocityDataPackType": "VlocityMatchingKeyObject",
            "VlocityMatchingRecordSourceKey": "OmniProcess/ARTL/NBAResponseToSolace/Procedure",
            "VlocityRecordSObjectType": "OmniProcess"
        },
        "VlocityDataPackType": "VlocityMatchingKeyObject",
        "VlocityMatchingRecordSourceKey": "OmniProcessElement/OmniProcess/ARTL/NBAResponseToSolace/Procedure/ConditionalBlock2",
        "VlocityRecordSObjectType": "OmniProcessElement"
    },
    "ParentElementName": "ConditionalBlock2",
    "ParentElementType": "Conditional Block",
    "PropertySetConfig": {
        "actionMessage": "",
        "chainOnStep": false,
        "disOnTplt": false,
        "elementValueMap": {
            "FRList": "=LIST(%SV_FailedResponse%)"
        },
        "executionConditionalFormula": "",
        "failOnStepError": false,
        "failureConditionalFormula": "",
        "label": "SetValues4",
        "responseJSONNode": "",
        "responseJSONPath": "",
        "show": null
    },
    "Type": "Set Values",
    "VlocityDataPackType": "SObject",
    "VlocityRecordSObjectType": "OmniProcessElement",
    "VlocityRecordSourceKey": "OmniProcessElement/OmniProcess/ARTL/NBAResponseToSolace/Procedure/SV_FailedResponseList"
}