[
    {
        "CurrencyIsoCode": "INR",
        "FilterGroup": 0,
        "FilterOperator": "=",
        "FilterValue": "taskId",
        "GlobalKey": "ARTL_DR_PMWorkwaysGetTask33152370324744806",
        "InputFieldName": "Id",
        "InputObjectName": "Task",
        "InputObjectQuerySequence": 1,
        "IsDisabled": false,
        "IsRequiredForUpsert": false,
        "IsUpsertKey": false,
        "Name": "ARTL_DR_PMWorkwaysGetTask",
        "OmniDataTransformationId": {
            "Name": "ARTL_DR_PMWorkwaysGetTask",
            "VlocityDataPackType": "VlocityMatchingKeyObject",
            "VlocityMatchingRecordSourceKey": "OmniDataTransform/ARTL_DR_PMWorkwaysGetTask",
            "VlocityRecordSObjectType": "OmniDataTransform"
        },
        "OutputCreationSequence": 0,
        "OutputFieldName": "Task",
        "OutputObjectName": "json",
        "VlocityDataPackType": "SObject",
        "VlocityRecordSObjectType": "OmniDataTransformItem"
    },
    {
        "CurrencyIsoCode": "INR",
        "FilterGroup": 0,
        "FilterOperator": "=",
        "FilterValue": "Task:WhatId",
        "GlobalKey": "ARTL_DR_PMWorkwaysGetTaskCustom6608",
        "InputFieldName": "Id",
        "InputObjectName": "Order",
        "InputObjectQuerySequence": 2,
        "IsDisabled": false,
        "IsRequiredForUpsert": false,
        "IsUpsertKey": false,
        "Name": "ARTL_DR_PMWorkwaysGetTask",
        "OmniDataTransformationId": {
            "Name": "ARTL_DR_PMWorkwaysGetTask",
            "VlocityDataPackType": "VlocityMatchingKeyObject",
            "VlocityMatchingRecordSourceKey": "OmniDataTransform/ARTL_DR_PMWorkwaysGetTask",
            "VlocityRecordSObjectType": "OmniDataTransform"
        },
        "OutputCreationSequence": 0,
        "OutputFieldName": "Order",
        "OutputObjectName": "json",
        "VlocityDataPackType": "SObject",
        "VlocityRecordSObjectType": "OmniDataTransformItem"
    },
    {
        "CurrencyIsoCode": "INR",
        "FormulaExpression": "DESERIALIZE(%ExecutionLog:ARTL_RequestPayload__c%)",
        "FormulaResultPath": "exePL",
        "FormulaSequence": 1,
        "GlobalKey": "ARTL_DR_PMWorkwaysGetTaskCustom9952",
        "IsDisabled": true,
        "IsRequiredForUpsert": false,
        "IsUpsertKey": false,
        "Name": "ARTL_DR_PMWorkwaysGetTask",
        "OmniDataTransformationId": {
            "Name": "ARTL_DR_PMWorkwaysGetTask",
            "VlocityDataPackType": "VlocityMatchingKeyObject",
            "VlocityMatchingRecordSourceKey": "OmniDataTransform/ARTL_DR_PMWorkwaysGetTask",
            "VlocityRecordSObjectType": "OmniDataTransform"
        },
        "OutputCreationSequence": 0,
        "OutputFieldName": "Formula",
        "OutputObjectName": "Formula",
        "VlocityDataPackType": "SObject",
        "VlocityRecordSObjectType": "OmniDataTransformItem"
    },
    {
        "CurrencyIsoCode": "INR",
        "GlobalKey": "ARTL_DR_PMWorkwaysGetTaskCustom5525",
        "InputFieldName": "ExecutionLog:ARTL_RequestPayload__c",
        "IsDisabled": true,
        "IsRequiredForUpsert": false,
        "IsUpsertKey": false,
        "Name": "ARTL_DR_PMWorkwaysGetTask",
        "OmniDataTransformationId": {
            "Name": "ARTL_DR_PMWorkwaysGetTask",
            "VlocityDataPackType": "VlocityMatchingKeyObject",
            "VlocityMatchingRecordSourceKey": "OmniDataTransform/ARTL_DR_PMWorkwaysGetTask",
            "VlocityRecordSObjectType": "OmniDataTransform"
        },
        "OutputCreationSequence": 1,
        "OutputFieldName": "ReqPayLoad",
        "OutputObjectName": "json",
        "VlocityDataPackType": "SObject",
        "VlocityRecordSObjectType": "OmniDataTransformItem"
    },
    {
        "CurrencyIsoCode": "INR",
        "DefaultValue": "null",
        "GlobalKey": "ARTL_DR_PMWorkwaysGetTask6925141623442357",
        "InputFieldName": "Task:ARTL_jeopardyReslnEta__c",
        "IsDisabled": false,
        "IsRequiredForUpsert": false,
        "IsUpsertKey": false,
        "Name": "ARTL_DR_PMWorkwaysGetTask",
        "OmniDataTransformationId": {
            "Name": "ARTL_DR_PMWorkwaysGetTask",
            "VlocityDataPackType": "VlocityMatchingKeyObject",
            "VlocityMatchingRecordSourceKey": "OmniDataTransform/ARTL_DR_PMWorkwaysGetTask",
            "VlocityRecordSObjectType": "OmniDataTransform"
        },
        "OutputCreationSequence": 1,
        "OutputFieldName": "jeopardyReslnEta",
        "OutputObjectName": "json",
        "VlocityDataPackType": "SObject",
        "VlocityRecordSObjectType": "OmniDataTransformItem"
    },
    {
        "CurrencyIsoCode": "INR",
        "DefaultValue": "null",
        "GlobalKey": "ARTL_DR_PMWorkwaysGetTask8855772243686686",
        "InputFieldName": "Order:ARTL_SOMOrderId__c",
        "IsDisabled": false,
        "IsRequiredForUpsert": false,
        "IsUpsertKey": false,
        "Name": "ARTL_DR_PMWorkwaysGetTask",
        "OmniDataTransformationId": {
            "Name": "ARTL_DR_PMWorkwaysGetTask",
            "VlocityDataPackType": "VlocityMatchingKeyObject",
            "VlocityMatchingRecordSourceKey": "OmniDataTransform/ARTL_DR_PMWorkwaysGetTask",
            "VlocityRecordSObjectType": "OmniDataTransform"
        },
        "OutputCreationSequence": 1,
        "OutputFieldName": "orderId",
        "OutputObjectName": "json",
        "VlocityDataPackType": "SObject",
        "VlocityRecordSObjectType": "OmniDataTransformItem"
    },
    {
        "CurrencyIsoCode": "INR",
        "DefaultValue": "null",
        "GlobalKey": "ARTL_DR_PMWorkwaysGetTask9083717770503541",
        "InputFieldName": "Task:ARTL_Remarks__c",
        "IsDisabled": false,
        "IsRequiredForUpsert": false,
        "IsUpsertKey": false,
        "Name": "ARTL_DR_PMWorkwaysGetTask",
        "OmniDataTransformationId": {
            "Name": "ARTL_DR_PMWorkwaysGetTask",
            "VlocityDataPackType": "VlocityMatchingKeyObject",
            "VlocityMatchingRecordSourceKey": "OmniDataTransform/ARTL_DR_PMWorkwaysGetTask",
            "VlocityRecordSObjectType": "OmniDataTransform"
        },
        "OutputCreationSequence": 1,
        "OutputFieldName": "remarks",
        "OutputObjectName": "json",
        "VlocityDataPackType": "SObject",
        "VlocityRecordSObjectType": "OmniDataTransformItem"
    },
    {
        "CurrencyIsoCode": "INR",
        "GlobalKey": "ARTL_DR_PMWorkwaysGetTaskCustom7076",
        "InputFieldName": "exePL",
        "IsDisabled": true,
        "IsRequiredForUpsert": false,
        "IsUpsertKey": false,
        "Name": "ARTL_DR_PMWorkwaysGetTask",
        "OmniDataTransformationId": {
            "Name": "ARTL_DR_PMWorkwaysGetTask",
            "VlocityDataPackType": "VlocityMatchingKeyObject",
            "VlocityMatchingRecordSourceKey": "OmniDataTransform/ARTL_DR_PMWorkwaysGetTask",
            "VlocityRecordSObjectType": "OmniDataTransform"
        },
        "OutputCreationSequence": 1,
        "OutputFieldName": "reqPL",
        "OutputObjectName": "json",
        "VlocityDataPackType": "SObject",
        "VlocityRecordSObjectType": "OmniDataTransformItem"
    },
    {
        "CurrencyIsoCode": "INR",
        "DefaultValue": "null",
        "GlobalKey": "ARTL_DR_PMWorkwaysGetTask7929559892604199",
        "InputFieldName": "Task:ARTL_TaskId__c",
        "IsDisabled": false,
        "IsRequiredForUpsert": false,
        "IsUpsertKey": false,
        "Name": "ARTL_DR_PMWorkwaysGetTask",
        "OmniDataTransformationId": {
            "Name": "ARTL_DR_PMWorkwaysGetTask",
            "VlocityDataPackType": "VlocityMatchingKeyObject",
            "VlocityMatchingRecordSourceKey": "OmniDataTransform/ARTL_DR_PMWorkwaysGetTask",
            "VlocityRecordSObjectType": "OmniDataTransform"
        },
        "OutputCreationSequence": 1,
        "OutputFieldName": "taskId",
        "OutputObjectName": "json",
        "VlocityDataPackType": "SObject",
        "VlocityRecordSObjectType": "OmniDataTransformItem"
    },
    {
        "CurrencyIsoCode": "INR",
        "DefaultValue": "null",
        "GlobalKey": "ARTL_DR_PMWorkwaysGetTask8625373506486202",
        "InputFieldName": "Task:Subject",
        "IsDisabled": false,
        "IsRequiredForUpsert": false,
        "IsUpsertKey": false,
        "Name": "ARTL_DR_PMWorkwaysGetTask",
        "OmniDataTransformationId": {
            "Name": "ARTL_DR_PMWorkwaysGetTask",
            "VlocityDataPackType": "VlocityMatchingKeyObject",
            "VlocityMatchingRecordSourceKey": "OmniDataTransform/ARTL_DR_PMWorkwaysGetTask",
            "VlocityRecordSObjectType": "OmniDataTransform"
        },
        "OutputCreationSequence": 1,
        "OutputFieldName": "taskName",
        "OutputObjectName": "json",
        "VlocityDataPackType": "SObject",
        "VlocityRecordSObjectType": "OmniDataTransformItem"
    },
    {
        "CurrencyIsoCode": "INR",
        "DefaultValue": "null",
        "GlobalKey": "ARTL_DR_PMWorkwaysGetTask19901858453781562",
        "InputFieldName": "Task:Status",
        "IsDisabled": false,
        "IsRequiredForUpsert": false,
        "IsUpsertKey": false,
        "Name": "ARTL_DR_PMWorkwaysGetTask",
        "OmniDataTransformationId": {
            "Name": "ARTL_DR_PMWorkwaysGetTask",
            "VlocityDataPackType": "VlocityMatchingKeyObject",
            "VlocityMatchingRecordSourceKey": "OmniDataTransform/ARTL_DR_PMWorkwaysGetTask",
            "VlocityRecordSObjectType": "OmniDataTransform"
        },
        "OutputCreationSequence": 1,
        "OutputFieldName": "taskStatus",
        "OutputObjectName": "json",
        "VlocityDataPackType": "SObject",
        "VlocityRecordSObjectType": "OmniDataTransformItem"
    },
    {
        "CurrencyIsoCode": "INR",
        "DefaultValue": "null",
        "GlobalKey": "ARTL_DR_PMWorkwaysGetTask10932613061744445",
        "InputFieldName": "Task:ARTL_TaskType__c",
        "IsDisabled": false,
        "IsRequiredForUpsert": false,
        "IsUpsertKey": false,
        "Name": "ARTL_DR_PMWorkwaysGetTask",
        "OmniDataTransformationId": {
            "Name": "ARTL_DR_PMWorkwaysGetTask",
            "VlocityDataPackType": "VlocityMatchingKeyObject",
            "VlocityMatchingRecordSourceKey": "OmniDataTransform/ARTL_DR_PMWorkwaysGetTask",
            "VlocityRecordSObjectType": "OmniDataTransform"
        },
        "OutputCreationSequence": 1,
        "OutputFieldName": "taskType",
        "OutputObjectName": "json",
        "VlocityDataPackType": "SObject",
        "VlocityRecordSObjectType": "OmniDataTransformItem"
    }
]