{
    "CurrencyIsoCode": "INR",
    "IsActive": true,
    "IsOmniScriptEmbeddable": false,
    "Name": "IP_ARTL_CreateNetwork_ChangeOrder",
    "OmniProcessId": {
        "Name": "ARTL_InboundSeibel",
        "VlocityDataPackType": "VlocityMatchingKeyObject",
        "VlocityMatchingRecordSourceKey": "OmniProcess/ARTL/CreateNetworkDisconnectOrder/Procedure",
        "VlocityRecordSObjectType": "OmniProcess"
    },
    "ParentElementId": {
        "Name": "ConditionalBlock1",
        "OmniProcessId": {
            "Name": "ARTL_InboundSeibel",
            "VlocityDataPackType": "VlocityMatchingKeyObject",
            "VlocityMatchingRecordSourceKey": "OmniProcess/ARTL/CreateNetworkDisconnectOrder/Procedure",
            "VlocityRecordSObjectType": "OmniProcess"
        },
        "VlocityDataPackType": "VlocityMatchingKeyObject",
        "VlocityMatchingRecordSourceKey": "OmniProcessElement/OmniProcess/ARTL/CreateNetworkDisconnectOrder/Procedure/ConditionalBlock1",
        "VlocityRecordSObjectType": "OmniProcessElement"
    },
    "ParentElementName": "ConditionalBlock1",
    "ParentElementType": "Conditional Block",
    "PropertySetConfig": {
        "actionMessage": "",
        "additionalInput": {
            "CaseId": "=%setCaseId:Id%"
        },
        "additionalOutput": {
        },
        "chainOnStep": false,
        "disOnTplt": false,
        "disableChainable": false,
        "executionConditionalFormula": "",
        "failOnStepError": true,
        "failureConditionalFormula": "",
        "failureResponse": {
        },
        "integrationProcedureKey": "ARTL_CreateNetwork_ChangeOrder",
        "label": "IntegrationProcedureAction1",
        "remoteOptions": {
        },
        "responseJSONNode": "",
        "responseJSONPath": "",
        "returnOnlyAdditionalOutput": false,
        "returnOnlyFailureResponse": false,
        "sendJSONNode": "",
        "sendJSONPath": "",
        "sendOnlyAdditionalInput": true,
        "show": null,
        "useFormulas": true
    },
    "Type": "Integration Procedure Action",
    "VlocityDataPackType": "SObject",
    "VlocityRecordSObjectType": "OmniProcessElement",
    "VlocityRecordSourceKey": "OmniProcessElement/OmniProcess/ARTL/CreateNetworkDisconnectOrder/Procedure/IP_ARTL_CreateNetwork_ChangeOrder"
}