{
    "AccountId": "0017200000SbByrAAF",
    "Attributes": {
        "ATT_BILL_PLAN": "100 GB",
        "ATT_CONTRACT_TERM": "12 Months",
        "ATT_INSTALLATION_LOCATION_ID": "a4i72000000QprhAAC",
        "ATT_LAST_MILE": "Single Last Mile",
        "ATT_MEDIA": "4G",
        "ATT_MPLS_ProductType_CME": null,
        "ATT_NUMBER_OF_LICENCES": "2",
        "ATT_PORT_BANDWIDTH": "2 Mbps",
        "ATT_ROUTING_TYPE": "Static",
        "ATT_SERVICE_TYPE": "Fully Managed",
        "ATT_VPN_NAME": null,
        "ATT_VPN_TOPOLOGY": "Hub & Spoke",
        "ATT_VPN_TYPE": "New"
    },
    "BillingAccountId": "0017200000TsnG1AAJ",
    "CustomerNeedByDate": "06/02/2024",
    "ParentOrderId": "8017200000V8n9lAAB",
    "PricebookEntryId": "01u72000000HYy9AAG",
    "QuoteId": "0Q0720000006rCvCAI",
    "RFSDate": "07/03/2024",
    "ServiceAccountId": "0017200000UNR7tAAH"
}