{
    "CurrencyIsoCode": "INR",
    "IsActive": true,
    "IsOmniScriptEmbeddable": false,
    "Name": "RACallVishalClass",
    "OmniProcessId": {
        "Name": "ARTL_CreateNetworkChangeOrder",
        "VlocityDataPackType": "VlocityMatchingKeyObject",
        "VlocityMatchingRecordSourceKey": "OmniProcess/ARTL_CreateNetwork/ChangeOrder/Procedure",
        "VlocityRecordSObjectType": "OmniProcess"
    },
    "PropertySetConfig": {
        "actionMessage": "",
        "additionalChainableResponse": {
        },
        "additionalInput": {
            "accountId": "%getCaseData:AccountID%",
            "caseId": "%CaseId%",
            "orderId": "%RAassetToOrder:CartId%",
            "recordType": "%getCaseData:RecTypeID%",
            "reqPayload": "%getCaseData:RequestPayload%",
            "samUser": "%DRGetSamUser:SAMUserId%"
        },
        "additionalOutput": {
        },
        "chainOnStep": false,
        "disOnTplt": false,
        "executionConditionalFormula": "",
        "failOnStepError": true,
        "failureConditionalFormula": "",
        "failureResponse": {
        },
        "label": "RemoteAction2",
        "remoteClass": "ARTL_NetWorkChangeOLIJSON",
        "remoteMethod": "readOLIPayload",
        "remoteOptions": {
        },
        "responseJSONNode": "",
        "responseJSONPath": "",
        "returnOnlyAdditionalOutput": false,
        "returnOnlyFailureResponse": false,
        "sendJSONNode": "",
        "sendJSONPath": "",
        "sendOnlyAdditionalInput": true,
        "show": null,
        "useFormulas": true
    },
    "Type": "Remote Action",
    "VlocityDataPackType": "SObject",
    "VlocityRecordSObjectType": "OmniProcessElement",
    "VlocityRecordSourceKey": "OmniProcessElement/OmniProcess/ARTL_CreateNetwork/ChangeOrder/Procedure/RACallVishalClass"
}