[
    {
        "%vlocity_namespace%__AdjustmentValue__c": "",
        "%vlocity_namespace%__Amount__c": 0,
        "%vlocity_namespace%__CalculationType__c": "Simple",
        "%vlocity_namespace%__Code__c": "VEPC_PLE_ARC_USD_0",
        "%vlocity_namespace%__CurrencyCode__c": "USD",
        "%vlocity_namespace%__DisplayText__c": "$ 0",
        "%vlocity_namespace%__EffectiveFromDate__c": "2023-12-31T18:30:00.000Z",
        "%vlocity_namespace%__EffectiveUntilDate__c": "",
        "%vlocity_namespace%__GlobalKey2__c": "22e734af-990a-0ac2-13c1-dc27f1353897",
        "%vlocity_namespace%__GlobalKey__c": "939ee1b9-6806-2c1f-5621-07b6db83ab3f",
        "%vlocity_namespace%__HelpText__c": "USD",
        "%vlocity_namespace%__IsActive__c": true,
        "%vlocity_namespace%__IsOverride__c": false,
        "%vlocity_namespace%__IsReusable__c": true,
        "%vlocity_namespace%__LoyaltyAmount__c": "",
        "%vlocity_namespace%__LoyaltyCode__c": "PTS",
        "%vlocity_namespace%__ObjectTypeId__c": {
            "%vlocity_namespace%__GlobalKey__c": "517349a3cdc1acf50617693e3ba33988",
            "VlocityDataPackType": "VlocityLookupMatchingKeyObject",
            "VlocityLookupRecordSourceKey": "%vlocity_namespace%__ObjectClass__c/517349a3cdc1acf50617693e3ba33988",
            "VlocityRecordSObjectType": "%vlocity_namespace%__ObjectClass__c"
        },
        "%vlocity_namespace%__OfferId__c": "",
        "%vlocity_namespace%__PerUsageAmount__c": 1,
        "%vlocity_namespace%__PerUsageMeasurementId__c": "",
        "%vlocity_namespace%__PerUsageUnitOfMeasure__c": "",
        "%vlocity_namespace%__PriceListId__c": {
            "%vlocity_namespace%__Code__c": "PL_USD",
            "VlocityDataPackType": "VlocityMatchingKeyObject",
            "VlocityMatchingRecordSourceKey": "%vlocity_namespace%__PriceList__c/PL_USD",
            "VlocityRecordSObjectType": "%vlocity_namespace%__PriceList__c"
        },
        "%vlocity_namespace%__PricingMatrixBindingData__c": "",
        "%vlocity_namespace%__PricingMatrixId__c": "",
        "%vlocity_namespace%__PricingVariableId__c": {
            "%vlocity_namespace%__Code__c": "REC_YRLY_STD_PRC",
            "VlocityDataPackType": "VlocityLookupMatchingKeyObject",
            "VlocityLookupRecordSourceKey": "%vlocity_namespace%__PricingVariable__c/REC_YRLY_STD_PRC",
            "VlocityRecordSObjectType": "%vlocity_namespace%__PricingVariable__c"
        },
        "%vlocity_namespace%__PricingVariableType__c": "Price",
        "%vlocity_namespace%__ProductId__c": "",
        "%vlocity_namespace%__PromotionId__c": "",
        "%vlocity_namespace%__RuleInfo__c": "",
        "%vlocity_namespace%__TimePlanId__c": "",
        "%vlocity_namespace%__VersionNumber__c": "2d7d8585-1842-19c3-aa7f-1f2739ffeaa8",
        "CurrencyIsoCode": "USD",
        "Name": "ARC-0.00-USD",
        "VlocityDataPackType": "SObject",
        "VlocityRecordSObjectType": "%vlocity_namespace%__PricingElement__c",
        "VlocityRecordSourceKey": "%vlocity_namespace%__PricingElement__c/939ee1b9-6806-2c1f-5621-07b6db83ab3f"
    },
    {
        "%vlocity_namespace%__AdjustmentValue__c": "",
        "%vlocity_namespace%__Amount__c": 0,
        "%vlocity_namespace%__CalculationType__c": "Simple",
        "%vlocity_namespace%__Code__c": "VEPC_PLE_ORC_USD_0",
        "%vlocity_namespace%__CurrencyCode__c": "USD",
        "%vlocity_namespace%__DisplayText__c": "$ 0",
        "%vlocity_namespace%__EffectiveFromDate__c": "2023-12-31T18:30:00.000Z",
        "%vlocity_namespace%__EffectiveUntilDate__c": "",
        "%vlocity_namespace%__GlobalKey2__c": "33520071-e1f7-fcb0-9cbe-9ce4242d4caf",
        "%vlocity_namespace%__GlobalKey__c": "691298f9-79a8-1675-c9ac-82ad28be663f",
        "%vlocity_namespace%__HelpText__c": "",
        "%vlocity_namespace%__IsActive__c": true,
        "%vlocity_namespace%__IsOverride__c": false,
        "%vlocity_namespace%__IsReusable__c": true,
        "%vlocity_namespace%__LoyaltyAmount__c": "",
        "%vlocity_namespace%__LoyaltyCode__c": "PTS",
        "%vlocity_namespace%__ObjectTypeId__c": {
            "%vlocity_namespace%__GlobalKey__c": "517349a3cdc1acf50617693e3ba33988",
            "VlocityDataPackType": "VlocityLookupMatchingKeyObject",
            "VlocityLookupRecordSourceKey": "%vlocity_namespace%__ObjectClass__c/517349a3cdc1acf50617693e3ba33988",
            "VlocityRecordSObjectType": "%vlocity_namespace%__ObjectClass__c"
        },
        "%vlocity_namespace%__OfferId__c": "",
        "%vlocity_namespace%__PerUsageAmount__c": 1,
        "%vlocity_namespace%__PerUsageMeasurementId__c": "",
        "%vlocity_namespace%__PerUsageUnitOfMeasure__c": "",
        "%vlocity_namespace%__PriceListId__c": {
            "%vlocity_namespace%__Code__c": "PL_USD",
            "VlocityDataPackType": "VlocityMatchingKeyObject",
            "VlocityMatchingRecordSourceKey": "%vlocity_namespace%__PriceList__c/PL_USD",
            "VlocityRecordSObjectType": "%vlocity_namespace%__PriceList__c"
        },
        "%vlocity_namespace%__PricingMatrixBindingData__c": "",
        "%vlocity_namespace%__PricingMatrixId__c": "",
        "%vlocity_namespace%__PricingVariableId__c": {
            "%vlocity_namespace%__Code__c": "OT_STD_PRC",
            "VlocityDataPackType": "VlocityLookupMatchingKeyObject",
            "VlocityLookupRecordSourceKey": "%vlocity_namespace%__PricingVariable__c/OT_STD_PRC",
            "VlocityRecordSObjectType": "%vlocity_namespace%__PricingVariable__c"
        },
        "%vlocity_namespace%__PricingVariableType__c": "Price",
        "%vlocity_namespace%__ProductId__c": "",
        "%vlocity_namespace%__PromotionId__c": "",
        "%vlocity_namespace%__RuleInfo__c": "",
        "%vlocity_namespace%__TimePlanId__c": "",
        "%vlocity_namespace%__VersionNumber__c": "89b45855-2f15-d9e5-57de-aec984646db8",
        "CurrencyIsoCode": "USD",
        "Name": "ORC-0.00-USD",
        "VlocityDataPackType": "SObject",
        "VlocityRecordSObjectType": "%vlocity_namespace%__PricingElement__c",
        "VlocityRecordSourceKey": "%vlocity_namespace%__PricingElement__c/691298f9-79a8-1675-c9ac-82ad28be663f"
    },
    {
        "%vlocity_namespace%__AdjustmentValue__c": "",
        "%vlocity_namespace%__Amount__c": 2323,
        "%vlocity_namespace%__CalculationType__c": "Simple",
        "%vlocity_namespace%__Code__c": "MRC-2323-USD",
        "%vlocity_namespace%__CurrencyCode__c": "USD",
        "%vlocity_namespace%__DisplayText__c": "$ 2323",
        "%vlocity_namespace%__EffectiveFromDate__c": "2023-12-31T18:30:00.000Z",
        "%vlocity_namespace%__EffectiveUntilDate__c": "",
        "%vlocity_namespace%__GlobalKey2__c": "95de258b-7f4a-3926-1370-2fe1e18638ff",
        "%vlocity_namespace%__GlobalKey__c": "6dd65c03-d373-68f7-eaac-4e7896c4ea87",
        "%vlocity_namespace%__HelpText__c": "",
        "%vlocity_namespace%__IsActive__c": true,
        "%vlocity_namespace%__IsOverride__c": false,
        "%vlocity_namespace%__IsReusable__c": true,
        "%vlocity_namespace%__LoyaltyAmount__c": "",
        "%vlocity_namespace%__LoyaltyCode__c": "PTS",
        "%vlocity_namespace%__ObjectTypeId__c": {
            "%vlocity_namespace%__GlobalKey__c": "517349a3cdc1acf50617693e3ba33988",
            "VlocityDataPackType": "VlocityLookupMatchingKeyObject",
            "VlocityLookupRecordSourceKey": "%vlocity_namespace%__ObjectClass__c/517349a3cdc1acf50617693e3ba33988",
            "VlocityRecordSObjectType": "%vlocity_namespace%__ObjectClass__c"
        },
        "%vlocity_namespace%__OfferId__c": "",
        "%vlocity_namespace%__PerUsageAmount__c": 1,
        "%vlocity_namespace%__PerUsageMeasurementId__c": "",
        "%vlocity_namespace%__PerUsageUnitOfMeasure__c": "",
        "%vlocity_namespace%__PriceListId__c": {
            "%vlocity_namespace%__Code__c": "PL_USD",
            "VlocityDataPackType": "VlocityMatchingKeyObject",
            "VlocityMatchingRecordSourceKey": "%vlocity_namespace%__PriceList__c/PL_USD",
            "VlocityRecordSObjectType": "%vlocity_namespace%__PriceList__c"
        },
        "%vlocity_namespace%__PricingMatrixBindingData__c": "",
        "%vlocity_namespace%__PricingMatrixId__c": "",
        "%vlocity_namespace%__PricingVariableId__c": {
            "%vlocity_namespace%__Code__c": "REC_YRLY_STD_PRC",
            "VlocityDataPackType": "VlocityLookupMatchingKeyObject",
            "VlocityLookupRecordSourceKey": "%vlocity_namespace%__PricingVariable__c/REC_YRLY_STD_PRC",
            "VlocityRecordSObjectType": "%vlocity_namespace%__PricingVariable__c"
        },
        "%vlocity_namespace%__PricingVariableType__c": "Price",
        "%vlocity_namespace%__ProductId__c": "",
        "%vlocity_namespace%__PromotionId__c": "",
        "%vlocity_namespace%__RuleInfo__c": "",
        "%vlocity_namespace%__TimePlanId__c": "",
        "%vlocity_namespace%__VersionNumber__c": "9a7a58e2-68e5-0ddc-6f65-aa1a1823f1ef",
        "CurrencyIsoCode": "USD",
        "Name": "MRC-2323-USD",
        "VlocityDataPackType": "SObject",
        "VlocityRecordSObjectType": "%vlocity_namespace%__PricingElement__c",
        "VlocityRecordSourceKey": "%vlocity_namespace%__PricingElement__c/6dd65c03-d373-68f7-eaac-4e7896c4ea87"
    },
    {
        "%vlocity_namespace%__AdjustmentValue__c": "",
        "%vlocity_namespace%__Amount__c": 4343,
        "%vlocity_namespace%__CalculationType__c": "Simple",
        "%vlocity_namespace%__Code__c": "ORC-4343-USD",
        "%vlocity_namespace%__CurrencyCode__c": "USD",
        "%vlocity_namespace%__DisplayText__c": "$ 4343",
        "%vlocity_namespace%__EffectiveFromDate__c": "2023-12-31T18:30:00.000Z",
        "%vlocity_namespace%__EffectiveUntilDate__c": "",
        "%vlocity_namespace%__GlobalKey2__c": "7d98b68d-1a3e-a2e4-8a7f-848d1d07a62d",
        "%vlocity_namespace%__GlobalKey__c": "f417dff4-0879-92db-b6fd-8568c5cc7c8b",
        "%vlocity_namespace%__HelpText__c": "",
        "%vlocity_namespace%__IsActive__c": true,
        "%vlocity_namespace%__IsOverride__c": false,
        "%vlocity_namespace%__IsReusable__c": true,
        "%vlocity_namespace%__LoyaltyAmount__c": "",
        "%vlocity_namespace%__LoyaltyCode__c": "PTS",
        "%vlocity_namespace%__ObjectTypeId__c": {
            "%vlocity_namespace%__GlobalKey__c": "517349a3cdc1acf50617693e3ba33988",
            "VlocityDataPackType": "VlocityLookupMatchingKeyObject",
            "VlocityLookupRecordSourceKey": "%vlocity_namespace%__ObjectClass__c/517349a3cdc1acf50617693e3ba33988",
            "VlocityRecordSObjectType": "%vlocity_namespace%__ObjectClass__c"
        },
        "%vlocity_namespace%__OfferId__c": "",
        "%vlocity_namespace%__PerUsageAmount__c": 1,
        "%vlocity_namespace%__PerUsageMeasurementId__c": "",
        "%vlocity_namespace%__PerUsageUnitOfMeasure__c": "",
        "%vlocity_namespace%__PriceListId__c": {
            "%vlocity_namespace%__Code__c": "PL_USD",
            "VlocityDataPackType": "VlocityMatchingKeyObject",
            "VlocityMatchingRecordSourceKey": "%vlocity_namespace%__PriceList__c/PL_USD",
            "VlocityRecordSObjectType": "%vlocity_namespace%__PriceList__c"
        },
        "%vlocity_namespace%__PricingMatrixBindingData__c": "",
        "%vlocity_namespace%__PricingMatrixId__c": "",
        "%vlocity_namespace%__PricingVariableId__c": {
            "%vlocity_namespace%__Code__c": "OT_STD_PRC",
            "VlocityDataPackType": "VlocityLookupMatchingKeyObject",
            "VlocityLookupRecordSourceKey": "%vlocity_namespace%__PricingVariable__c/OT_STD_PRC",
            "VlocityRecordSObjectType": "%vlocity_namespace%__PricingVariable__c"
        },
        "%vlocity_namespace%__PricingVariableType__c": "Price",
        "%vlocity_namespace%__ProductId__c": "",
        "%vlocity_namespace%__PromotionId__c": "",
        "%vlocity_namespace%__RuleInfo__c": "",
        "%vlocity_namespace%__TimePlanId__c": "",
        "%vlocity_namespace%__VersionNumber__c": "1cffa4ae-99de-f7df-7025-6ec5cc24366a",
        "CurrencyIsoCode": "USD",
        "Name": "ORC-4343-USD",
        "VlocityDataPackType": "SObject",
        "VlocityRecordSObjectType": "%vlocity_namespace%__PricingElement__c",
        "VlocityRecordSourceKey": "%vlocity_namespace%__PricingElement__c/f417dff4-0879-92db-b6fd-8568c5cc7c8b"
    }
]